nanobot/__init__.py
nanobot/__main__.py
nanobot/async_engine.py
nanobot/config.py
nanobot/main.py
nanobot/plugins.py
nanobot/adapters/__init__.py
nanobot/adapters/base.py
nanobot/adapters/mock.py
nanobot/core/__init__.py
nanobot/core/engine.py
nanobot/core/node.py
nanobot/core/sensors.py
nanobot/nodes/__init__.py
nanobot/nodes/base.py
nanobot/nodes/exploration.py
nanobot/nodes/explorer.py
nanobot/nodes/memory.py
nanobot/nodes/navigation.py
nanobot/nodes/pathfinding.py
nanobot/nodes/physiques.py
nanobot/nodes/safety.py
nanobot/nodes/scan.py
nanobot/nodes/wall_follower.py
nanobot/nodes/physique/__init__.py
nanobot/nodes/physique/corner.py
nanobot/nodes/physique/forward.py
nanobot/nodes/physique/friction.py
nanobot/nodes/physique/intersection.py
nanobot/nodes/physique/stuck.py
nanobot/nodes/physique/wall.py
nanobot/tests/__init__.py
nanobot/tests/test_engine.py
nanobot/tests/test_nodes.py
nanobot-0.4.1.dist-info/licenses/LICENSE
nanobot-0.4.1.dist-info/METADATA
nanobot-0.4.1.dist-info/WHEEL
nanobot-0.4.1.dist-info/entry_points.txt
nanobot-0.4.1.dist-info/top_level.txt
nanobot-0.4.1.dist-info/RECORD
